dotapi/__init__.py
dotapi/__main__.py
dotapi/_base_client.py
dotapi/_client.py
dotapi/_compat.py
dotapi/_constants.py
dotapi/_exceptions.py
dotapi/_extras/__init__.py
dotapi/_extras/_common.py
dotapi/_extras/numpy_proxy.py
dotapi/_extras/pandas_proxy.py
dotapi/_files.py
dotapi/_legacy_response.py
dotapi/_models.py
dotapi/_module_client.py
dotapi/_qs.py
dotapi/_resource.py
dotapi/_response.py
dotapi/_streaming.py
dotapi/_types.py
dotapi/_utils/__init__.py
dotapi/_utils/_logs.py
dotapi/_utils/_proxy.py
dotapi/_utils/_reflection.py
dotapi/_utils/_streams.py
dotapi/_utils/_sync.py
dotapi/_utils/_transform.py
dotapi/_utils/_typing.py
dotapi/_utils/_utils.py
dotapi/_version.py
dotapi/cli/__init__.py
dotapi/cli/_api/__init__.py
dotapi/cli/_api/_main.py
dotapi/cli/_api/audio.py
dotapi/cli/_api/chat/__init__.py
dotapi/cli/_api/chat/completions.py
dotapi/cli/_api/completions.py
dotapi/cli/_api/files.py
dotapi/cli/_api/image.py
dotapi/cli/_api/models.py
dotapi/cli/_cli.py
dotapi/cli/_errors.py
dotapi/cli/_models.py
dotapi/cli/_progress.py
dotapi/cli/_tools/__init__.py
dotapi/cli/_tools/_main.py
dotapi/cli/_tools/fine_tunes.py
dotapi/cli/_tools/migrate.py
dotapi/cli/_utils.py
dotapi/lib/.keep
dotapi/lib/_old_api.py
dotapi/lib/_validators.py
dotapi/lib/azure.py
dotapi/lib/streaming/__init__.py
dotapi/lib/streaming/_assistants.py
dotapi/pagination.py
dotapi/py.typed
dotapi/resources/__init__.py
dotapi/resources/audio/__init__.py
dotapi/resources/audio/audio.py
dotapi/resources/audio/speech.py
dotapi/resources/audio/transcriptions.py
dotapi/resources/audio/translations.py
dotapi/resources/batches.py
dotapi/resources/beta/__init__.py
dotapi/resources/beta/assistants.py
dotapi/resources/beta/beta.py
dotapi/resources/beta/threads/__init__.py
dotapi/resources/beta/threads/messages.py
dotapi/resources/beta/threads/runs/__init__.py
dotapi/resources/beta/threads/runs/runs.py
dotapi/resources/beta/threads/runs/steps.py
dotapi/resources/beta/threads/threads.py
dotapi-1.0.0.dist-info/LICENSE
dotapi-1.0.0.dist-info/METADATA
dotapi-1.0.0.dist-info/WHEEL
dotapi-1.0.0.dist-info/entry_points.txt
dotapi-1.0.0.dist-info/RECORD
